setup.py
ssd1327.py
micropython_ssd1327.egg-info/PKG-INFO
micropython_ssd1327.egg-info/SOURCES.txt
micropython_ssd1327.egg-info/dependency_links.txt
micropython_ssd1327.egg-info/top_level.txt